.gitignore
.travis.yml
CHANGES.rst
CONTRIBUTORS.rst
MANIFEST.in
README.rst
bootstrap.py
buildout.cfg
setup.py
travis.cfg
buildout.d/base.cfg
buildout.d/checkouts.cfg
buildout.d/development.cfg
buildout.d/jenkins.cfg
buildout.d/sources.cfg
buildout.d/versions.cfg
docs/LICENSE.GPL
docs/LICENSE.rst
docs/example-faceted-config.xml
src/collective/__init__.py
src/collective.contact.facetednav.egg-info/PKG-INFO
src/collective.contact.facetednav.egg-info/SOURCES.txt
src/collective.contact.facetednav.egg-info/dependency_links.txt
src/collective.contact.facetednav.egg-info/entry_points.txt
src/collective.contact.facetednav.egg-info/namespace_packages.txt
src/collective.contact.facetednav.egg-info/not-zip-safe
src/collective.contact.facetednav.egg-info/requires.txt
src/collective.contact.facetednav.egg-info/top_level.txt
src/collective/contact/__init__.py
src/collective/contact/facetednav/__init__.py
src/collective/contact/facetednav/configure.zcml
src/collective/contact/facetednav/interfaces.py
src/collective/contact/facetednav/minimal.zcml
src/collective/contact/facetednav/setuphandlers.py
src/collective/contact/facetednav/testing.py
src/collective/contact/facetednav/testing.zcml
src/collective/contact/facetednav/vocabularies.py
src/collective/contact/facetednav/browser/__init__.py
src/collective/contact/facetednav/browser/configure.zcml
src/collective/contact/facetednav/browser/interfaces.py
src/collective/contact/facetednav/browser/preview-heldposition.pt
src/collective/contact/facetednav/browser/preview-items.pt
src/collective/contact/facetednav/browser/preview-organization.pt
src/collective/contact/facetednav/browser/preview-person.pt
src/collective/contact/facetednav/browser/query.pt
src/collective/contact/facetednav/browser/subtyper.py
src/collective/contact/facetednav/browser/view.py
src/collective/contact/facetednav/browser/actions/__init__.py
src/collective/contact/facetednav/browser/actions/action.pt
src/collective/contact/facetednav/browser/actions/actions.pt
src/collective/contact/facetednav/browser/actions/base.py
src/collective/contact/facetednav/browser/actions/batchaction.pt
src/collective/contact/facetednav/browser/actions/batchactions.pt
src/collective/contact/facetednav/browser/actions/configure.zcml
src/collective/contact/facetednav/browser/actions/delete.py
src/collective/contact/facetednav/browser/actions/delete.zcml
src/collective/contact/facetednav/browser/actions/edit.py
