Metadata-Version: 2.1
Name: collective.contact.facetednav
Version: 1.1.8
Summary: Faceted navigation view for collective.contact.core directory
Home-page: http://pypi.python.org/pypi/collective.contact.facetednav
Author: Cédric Messiant
Author-email: cedricmessiant@ecreall.com
License: GPL
Keywords: contact,dexterity,faceted,search
Platform: UNKNOWN
Classifier: Environment :: Web Environment
Classifier: Framework :: Plone
Classifier: Framework :: Plone :: 4.3
Classifier: Programming Language :: Python
Classifier: Programming Language :: Python :: 2.7
Provides-Extra: test
